.coveragerc
.gitignore
.isort.cfg
.pre-commit-config.yaml
AUTHORS.rst
CHANGELOG.rst
LICENSE.txt
README.md
requirements.txt
scheme.jpeg
setup.cfg
setup.py
docs/Makefile
docs/authors.rst
docs/changelog.rst
docs/conf.py
docs/index.rst
docs/license.rst
docs/_static/.gitignore
src/img2rag/__init__.py
src/img2rag/base.py
src/img2rag/skeleton.py
src/img2rag/utils.py
src/img2rag.egg-info/PKG-INFO
src/img2rag.egg-info/SOURCES.txt
src/img2rag.egg-info/dependency_links.txt
src/img2rag.egg-info/not-zip-safe
src/img2rag.egg-info/requires.txt
src/img2rag.egg-info/top_level.txt
tests/conftest.py
tests/test_skeleton.py