Metadata-Version: 2.1
Name: img2rag
Version: 1.0.0
Summary: Converts images into corresponding Region Adjacency Graphs
Home-page: https://github.com/LeviBorodenko/img2rag
Author: Levi Borodenko
Author-email: Levi.borodenko@gmail.com
License: mit
Project-URL: Documentation, https://github.com/LeviBorodenko/img2rag
Platform: any
Classifier: Development Status :: 4 - Beta
Classifier: Programming Language :: Python
Provides-Extra: testing
